aiida_diff/__init__.py
aiida_diff/calculations.py
aiida_diff/cli.py
aiida_diff/helpers.py
aiida_diff/parsers.py
aiida_diff/data/__init__.py
aiida_diff-2.0.0.dist-info/entry_points.txt
aiida_diff-2.0.0.dist-info/LICENSE
aiida_diff-2.0.0.dist-info/WHEEL
aiida_diff-2.0.0.dist-info/METADATA
aiida_diff-2.0.0.dist-info/RECORD
